gitorg/__init__.py
gitorg/__main__.py
gitorg/cli.py
gitorg/core.py
gitorg/file.py
gitorg/git.py
gitorg/protocols.py
gitorg-0.8.0.dist-info/DESCRIPTION.rst
gitorg-0.8.0.dist-info/METADATA
gitorg-0.8.0.dist-info/RECORD
gitorg-0.8.0.dist-info/WHEEL
gitorg-0.8.0.dist-info/entry_points.txt
gitorg-0.8.0.dist-info/metadata.json
gitorg-0.8.0.dist-info/top_level.txt
