Metadata-Version: 2.0
Name: gitorg
Version: 0.8.0
Summary: Use git for organizations!
Home-page: https://github.com/Mariocj89/gitorg
Author: Mario Corchero
Author-email: mariocj89@gmail.com
License: MIT
Keywords: github,sync,workspace
Platform: UNKNOWN
Classifier: Development Status :: 3 - Alpha
Classifier: Environment :: Console
Classifier: Intended Audience :: Developers
Classifier: License :: OSI Approved :: MIT License
Classifier: Operating System :: OS Independent
Classifier: Programming Language :: Python :: 3.6
Classifier: Topic :: Software Development :: Version Control
Requires-Dist: PyGithub
Requires-Dist: PyYAML
